hmr/__init__.py
hmr/config.py
hmr/formatters.py
hmr/main.py
hmr/models.py
hmr/scripts/__init__.py
hmr/scripts/send_notifications.py
hanging_merge_requests-1.0.2.dist-info/LICENSE
hanging_merge_requests-1.0.2.dist-info/METADATA
hanging_merge_requests-1.0.2.dist-info/WHEEL
hanging_merge_requests-1.0.2.dist-info/entry_points.txt
hanging_merge_requests-1.0.2.dist-info/top_level.txt
hanging_merge_requests-1.0.2.dist-info/RECORD
