Metadata-Version: 2.1
Name: hanging-merge-requests
Version: 1.0.2
Summary: Emojiful daily summaries of open merge requests directly in your Slack
Home-page: https://github.com/Webinterpret/hanging-merge-requests
License: UNKNOWN
Platform: UNKNOWN
Classifier: Development Status :: 4 - Beta
Classifier: Environment :: Console
Classifier: Intended Audience :: Developers
Classifier: License :: OSI Approved :: MIT License
Classifier: Natural Language :: English
Classifier: Operating System :: OS Independent
Classifier: Programming Language :: Python :: 3 :: Only
Classifier: Programming Language :: Python :: 3.5
Classifier: Programming Language :: Python :: 3.6
Classifier: Programming Language :: Python :: 3.7
Classifier: Programming Language :: Python :: 3.8
Classifier: Programming Language :: Python
Classifier: Topic :: Communications :: Chat
Classifier: Topic :: Software Development :: Build Tools
Classifier: Topic :: Software Development
Requires-Dist: python-gitlab (==1.7.0)
Requires-Dist: arrow
Requires-Dist: humanize
